setup.py
pytransform/__init__.py
pytransform/_pytransform.so
snb_plugin/SnbFaaSSim.py
snb_plugin/__init__.py
snb_plugin/config.py
snb_plugin.egg-info/PKG-INFO
snb_plugin.egg-info/SOURCES.txt
snb_plugin.egg-info/dependency_links.txt
snb_plugin.egg-info/entry_points.txt
snb_plugin.egg-info/top_level.txt
snb_plugin/etl/__init__.py
snb_plugin/etl/comparison.py
snb_plugin/etl/compat.py
snb_plugin/etl/config.py
snb_plugin/etl/errors.py
snb_plugin/etl/io/__init__.py
snb_plugin/etl/io/avro.py
snb_plugin/etl/io/base.py
snb_plugin/etl/io/bcolz.py
snb_plugin/etl/io/csv.py
snb_plugin/etl/io/csv_py2.py
snb_plugin/etl/io/csv_py3.py
snb_plugin/etl/io/db.py
snb_plugin/etl/io/db_create.py
snb_plugin/etl/io/db_utils.py
snb_plugin/etl/io/gsheet.py
snb_plugin/etl/io/html.py
snb_plugin/etl/io/json.py
snb_plugin/etl/io/numpy.py
snb_plugin/etl/io/pandas.py
snb_plugin/etl/io/pickle.py
snb_plugin/etl/io/pytables.py
snb_plugin/etl/io/remotes.py
snb_plugin/etl/io/sources.py
snb_plugin/etl/io/text.py
snb_plugin/etl/io/whoosh.py
snb_plugin/etl/io/xls.py
snb_plugin/etl/io/xlsx.py
snb_plugin/etl/io/xlutils_view.py
snb_plugin/etl/io/xml.py
snb_plugin/etl/test/__init__.py
snb_plugin/etl/test/conftest.py
snb_plugin/etl/test/failonerror.py
snb_plugin/etl/test/helpers.py
snb_plugin/etl/test/test_comparison.py
snb_plugin/etl/test/test_fluent.py
snb_plugin/etl/test/test_helpers.py
snb_plugin/etl/test/test_interactive.py
snb_plugin/etl/test/io/__init__.py
snb_plugin/etl/test/io/test_avro.py
snb_plugin/etl/test/io/test_avro_schemas.py
snb_plugin/etl/test/io/test_bcolz.py
snb_plugin/etl/test/io/test_csv.py
snb_plugin/etl/test/io/test_csv_unicode.py
snb_plugin/etl/test/io/test_db.py
snb_plugin/etl/test/io/test_db_create.py
snb_plugin/etl/test/io/test_db_server.py
snb_plugin/etl/test/io/test_gsheet.py
snb_plugin/etl/test/io/test_html.py
snb_plugin/etl/test/io/test_html_unicode.py
snb_plugin/etl/test/io/test_json.py
snb_plugin/etl/test/io/test_json_unicode.py
snb_plugin/etl/test/io/test_jsonl.py
snb_plugin/etl/test/io/test_numpy.py
snb_plugin/etl/test/io/test_pandas.py
snb_plugin/etl/test/io/test_pickle.py
snb_plugin/etl/test/io/test_pytables.py
