Metadata-Version: 2.1
Name: snb-plugin
Version: 1.6.6
Summary: smart-notebook plugin
Home-page: http://smartnotebook.tech/
Author: wang xin yi
Author-email: wangxinyi@smartnotebook.tech
